chromia_console_client/__init__.py
chromia_console_client/api_client.py
chromia_console_client/api_response.py
chromia_console_client/configuration.py
chromia_console_client/exceptions.py
chromia_console_client/py.typed
chromia_console_client/rest.py
chromia_console_client/api/__init__.py
chromia_console_client/api/chromia_vector_db_api.py
chromia_console_client/models/__init__.py
chromia_console_client/models/create_vector_batch_request.py
chromia_console_client/models/create_vector_request.py
chromia_console_client/models/error_detail.py
chromia_console_client/models/error_response.py
chromia_console_client/models/get_closest_response.py
chromia_console_client/models/image_embedding_batch_request.py
chromia_console_client/models/image_embedding_request.py
chromia_console_client/models/news_headline_with_embedding.py
chromia_console_client/models/payload_distance.py
chromia_console_client/models/transaction_result_body.py
chromia_console_client/models/vector_collection.py
chromia_console_client/models/vector_collection_change.py
chromia_console_client/models/vector_filter_request.py
chromia_console_client/models/vector_request.py
chromia_console_client-0.0.2.dist-info/METADATA
chromia_console_client-0.0.2.dist-info/WHEEL
chromia_console_client-0.0.2.dist-info/top_level.txt
chromia_console_client-0.0.2.dist-info/RECORD
